cloudexplain/__init__.py
cloudexplain/create_model_metadata.py
cloudexplain/azure/__init__.py
cloudexplain/azure/explain.py
cloudexplain/azure/utils.py
cloudexplain-0.1.0rc6.dist-info/licenses/LICENSE
cloudexplain-0.1.0rc6.dist-info/METADATA
cloudexplain-0.1.0rc6.dist-info/WHEEL
cloudexplain-0.1.0rc6.dist-info/top_level.txt
cloudexplain-0.1.0rc6.dist-info/RECORD
