Metadata-Version: 2.4
Name: cloudexplain
Version: 0.1.0rc6
Summary: A package for explaining cloud-based solutions provided by cloudexplain GmbH.
Author-email: cloudexplain <info@cloudexplain.eu>
License: MIT License
Project-URL: Homepage, https://www.cloudexplain.eu
Project-URL: Repository, https://github.com/cloudexplain/cloudexplain
Keywords: cloud,explain,machine learning,AI
Classifier: Programming Language :: Python :: 3
Classifier: License :: OSI Approved :: MIT License
Classifier: Operating System :: OS Independent
License-File: LICENSE
Provides-Extra: azure
Requires-Dist: azure-identity; extra == "azure"
Requires-Dist: azure-mgmt-resource; extra == "azure"
Requires-Dist: azure-mgmt-storage; extra == "azure"
Requires-Dist: azure-storage-blob; extra == "azure"
Requires-Dist: azure-storage-file; extra == "azure"
Requires-Dist: azure-storage-file-datalake; extra == "azure"
Provides-Extra: sklearn
Requires-Dist: scikit-learn; extra == "sklearn"
Provides-Extra: xgboost
Requires-Dist: xgboost; extra == "xgboost"
Provides-Extra: catboost
Requires-Dist: catboost; extra == "catboost"
Provides-Extra: lightgbm
Requires-Dist: lightgbm; extra == "lightgbm"
Provides-Extra: pytorch
Requires-Dist: torch; extra == "pytorch"
Requires-Dist: torchvision; extra == "pytorch"
Provides-Extra: tensorflow
Requires-Dist: tensorflow; extra == "tensorflow"
Provides-Extra: test
Requires-Dist: scikit-learn; extra == "test"
Requires-Dist: xgboost; extra == "test"
Requires-Dist: catboost; extra == "test"
Requires-Dist: lightgbm; extra == "test"
Requires-Dist: torch; extra == "test"
Requires-Dist: torchvision; extra == "test"
Requires-Dist: tensorflow; extra == "test"
Requires-Dist: shap; extra == "test"
Requires-Dist: pytest; extra == "test"
Dynamic: license-file
